isage_agentic-0.1.0.0.dist-info/licenses/LICENSE
sage_libs/__init__.py
sage_libs/sage_agentic/__init__.py
sage_libs/sage_agentic/agents/__init__.py
sage_libs/sage_agentic/agents/agent.py
sage_libs/sage_agentic/agents/examples.py
sage_libs/sage_agentic/agents/action/mcp_registry.py
sage_libs/sage_agentic/agents/action/mcp_server.py
sage_libs/sage_agentic/agents/action/tool_selection/__init__.py
sage_libs/sage_agentic/agents/action/tool_selection/base.py
sage_libs/sage_agentic/agents/action/tool_selection/dfsdt_selector.py
sage_libs/sage_agentic/agents/action/tool_selection/embedding_selector.py
sage_libs/sage_agentic/agents/action/tool_selection/gorilla_selector.py
sage_libs/sage_agentic/agents/action/tool_selection/hybrid_selector.py
sage_libs/sage_agentic/agents/action/tool_selection/keyword_selector.py
sage_libs/sage_agentic/agents/action/tool_selection/registry.py
sage_libs/sage_agentic/agents/action/tool_selection/schemas.py
sage_libs/sage_agentic/agents/action/tool_selection/retriever/__init__.py
sage_libs/sage_agentic/agents/action/tool_selection/retriever/cache.py
sage_libs/sage_agentic/agents/action/tool_selection/retriever/vector_index.py
sage_libs/sage_agentic/agents/bots/__init__.py
sage_libs/sage_agentic/agents/bots/answer_bot.py
sage_libs/sage_agentic/agents/bots/critic_bot.py
sage_libs/sage_agentic/agents/bots/question_bot.py
sage_libs/sage_agentic/agents/bots/searcher_bot.py
sage_libs/sage_agentic/agents/planning/__init__.py
sage_libs/sage_agentic/agents/planning/base.py
sage_libs/sage_agentic/agents/planning/dependency_graph.py
sage_libs/sage_agentic/agents/planning/hierarchical_planner.py
sage_libs/sage_agentic/agents/planning/react_planner.py
sage_libs/sage_agentic/agents/planning/schemas.py
sage_libs/sage_agentic/agents/planning/simple_llm_planner.py
sage_libs/sage_agentic/agents/planning/timing_decider.py
sage_libs/sage_agentic/agents/planning/tot_planner.py
sage_libs/sage_agentic/agents/planning/utils/__init__.py
sage_libs/sage_agentic/agents/planning/utils/repair.py
isage_agentic-0.1.0.0.dist-info/METADATA
isage_agentic-0.1.0.0.dist-info/WHEEL
isage_agentic-0.1.0.0.dist-info/top_level.txt
isage_agentic-0.1.0.0.dist-info/RECORD
