Metadata-Version: 2.4
Name: isage-agentic
Version: 0.1.0.0
Summary: SAGE Agentic Framework - Agent framework, planning, tool selection, and workflow
Author-email: IntelliStream Team <shuhao_zhang@hust.edu.cn>
License-Expression: MIT
Project-URL: Homepage, https://github.com/intellistream/sage-agentic
Project-URL: Repository, https://github.com/intellistream/sage-agentic
Keywords: agentic,agent,planning,tool-selection,workflow,LLM,AI
Requires-Python: >=3.10
License-File: LICENSE
Requires-Dist: pydantic>=2.0.0
Requires-Dist: typing-extensions>=4.0.0
Requires-Dist: isage-libs>=0.2.0
Provides-Extra: dev
Requires-Dist: pytest>=7.0.0; extra == "dev"
Requires-Dist: pytest-cov>=4.0.0; extra == "dev"
Requires-Dist: ruff>=0.8.4; extra == "dev"
Requires-Dist: mypy>=1.0.0; extra == "dev"
Provides-Extra: llm
Requires-Dist: openai>=1.0.0; extra == "llm"
Requires-Dist: anthropic>=0.20.0; extra == "llm"
Provides-Extra: full
Requires-Dist: isage-agentic[dev,llm]; extra == "full"
Dynamic: license-file
